{
  "defaultSeverity": "error",
  "extends": [
    "tslint:latest",
    "tslint-react",
    "tslint-config-prettier"
  ],
  "linterOptions": {
    "exclude": [
      "types/**/*.d.ts"
    ]
  },
  "jsRules": {},
  "rules": {
    "no-implicit-dependencies": false,
    "interface-name": [true, "never-prefix"],
    "interface-over-type-literal": false,
    "member-access": [true, "no-public"],
    "object-literal-sort-keys": false,
    "no-submodule-imports": false,
    "ordered-imports": false,
    "variable-name": [true, "check-format", "allow-pascal-case", "allow-leading-underscore"],
    "array-type": [true, "array"],
    "no-angle-bracket-type-assertion": true,
    "jsx-no-lambda": false,
    "triple-equals": true,
    "jsx-ban-elements": {
      "options": [
        ["^form$", "Use app/components/forms/Form instead."]
      ]
    },
    "jsx-boolean-value": false,
    "prefer-conditional-expression": false,
    "no-empty-interface": false,
    "no-shadowed-variable": false,
    "no-unused-expression": false,
    "callable-types": false,
    "no-any": true
  }
}
